[
  {
    "href": "http://t5.w-ga.me/FcDec23dl88b",
    "date": "2024-12-24"
  },
  {
    "href": "http://t5.w-ga.me/WCBDec23cb08g",
    "date": "2024-12-24"
  },
  {
    "href": "http://t5.w-ga.me/GvawDec23bl08hg",
    "date": "2024-12-24"
  },
  {
    "href": "http://t5.w-ga.me/GeDec22l097vb7",
    "date": "2024-12-23"
  },
  {
    "href": "http://t5.w-ga.me/FcDec22bpo08",
    "date": "2024-12-23"
  },
  {
    "href": "http://t5.w-ga.me/FcDec22b9g7yha",
    "date": "2024-12-23"
  },
  {
    "href": "http://t5.w-ga.me/FcDec22c0978h",
    "date": "2024-12-23"
  },
  {
    "href": "http://t5.w-ga.me/GvawDec22lb078g",
    "date": "2024-12-23"
  },
  {
    "href": "http://t5.w-ga.me/SfDec21gda57",
    "date": "2024-12-22"
  },
  {
    "href": "http://t5.w-ga.me/FcDec21c0z7bhg",
    "date": "2024-12-22"
  },
  {
    "href": "http://t5.w-ga.me/FcDec21xb08g",
    "date": "2024-12-22"
  },
  {
    "href": "http://t5.w-ga.me/ScDec21xvs5",
    "date": "2024-12-22"
  },
  {
    "href": "http://t5.w-ga.me/FtDec21bo908gx",
    "date": "2024-12-22"
  },
  {
    "href": "http://t5.w-ga.me/FcDec20bv097s",
    "date": "2024-12-21"
  },
  {
    "href": "http://t5.w-ga.me/FcDec20xb08z",
    "date": "2024-12-21"
  },
  {
    "href": "http://t5.w-ga.me/FcDec20cbog87d",
    "date": "2024-12-21"
  },
  {
    "href": "http://t5.w-ga.me/FcDec20cvc08g",
    "date": "2024-12-21"
  },
  {
    "href": "http://t5.w-ga.me/FcDec20x08bhg",
    "date": "2024-12-20"
  },
  {
    "href": "http://t5.w-ga.me/FcDec19c087bg",
    "date": "2024-12-20"
  },
  {
    "href": "http://t5.w-ga.me/FcDec19bo87yhc",
    "date": "2024-12-20"
  },
  {
    "href": "http://t5.w-ga.me/FcDec19vz5sbs",
    "date": "2024-12-20"
  },
  {
    "href": "http://t5.w-ga.me/LWDec19vo97dsx",
    "date": "2024-12-20"
  },
  {
    "href": "http://t5.w-ga.me/FcDec19coz08s",
    "date": "2024-12-20"
  },
  {
    "href": "http://t5.w-ga.me/GeDec18bvl087",
    "date": "2024-12-19"
  },
  {
    "href": "http://t5.w-ga.me/FcDec18zl0b7g",
    "date": "2024-12-19"
  },
  {
    "href": "http://t5.w-ga.me/FcDec18bv68vd",
    "date": "2024-12-19"
  },
  {
    "href": "http://t5.w-ga.me/FcDec18xla0hnc",
    "date": "2024-12-19"
  },
  {
    "href": "http://t5.w-ga.me/GvawDec18fdkl9y",
    "date": "2024-12-19"
  },
  {
    "href": "http://t5.w-ga.me/SfDec17xl0b78ug",
    "date": "2024-12-18"
  },
  {
    "href": "http://t5.w-ga.me/FcDec17b08gd",
    "date": "2024-12-18"
  },
  {
    "href": "http://t5.w-ga.me/LWDec17zl08g",
    "date": "2024-12-18"
  },
  {
    "href": "http://t5.w-ga.me/FtDec17bl0uhf",
    "date": "2024-12-18"
  },
  {
    "href": "http://t5.w-ga.me/GeDec16b0jngx",
    "date": "2024-12-17"
  },
  {
    "href": "http://t5.w-ga.me/FcDec16bgzl08",
    "date": "2024-12-17"
  },
  {
    "href": "http://t5.w-ga.me/FcDec16cl0ubg",
    "date": "2024-12-17"
  },
  {
    "href": "http://t5.w-ga.me/WCBDec16bgl0uz",
    "date": "2024-12-17"
  },
  {
    "href": "http://t5.w-ga.me/GvawDec16glv0h",
    "date": "2024-12-17"
  },
  {
    "href": "http://t5.w-ga.me/GeDec15blh089",
    "date": "2024-12-16"
  },
  {
    "href": "http://t5.w-ga.me/FcDec15glf8ru",
    "date": "2024-12-16"
  },
  {
    "href": "http://t5.w-ga.me/FcDec15ho87bz",
    "date": "2024-12-16"
  },
  {
    "href": "http://t5.w-ga.me/FcDec15sdkl0",
    "date": "2024-12-16"
  },
  {
    "href": "http://t5.w-ga.me/GvawDec15zlx08f",
    "date": "2024-12-16"
  },
  {
    "href": "http://t5.w-ga.me/SfDec14lc08d",
    "date": "2024-12-15"
  },
  {
    "href": "http://t5.w-ga.me/FcDec14ln907g",
    "date": "2024-12-15"
  },
  {
    "href": "http://t5.w-ga.me/FcDec14k0zyh",
    "date": "2024-12-15"
  },
  {
    "href": "http://t5.w-ga.me/ScDec14clz08",
    "date": "2024-12-15"
  },
  {
    "href": "http://t5.w-ga.me/FtDec14zlx97",
    "date": "2024-12-15"
  },
  {
    "href": "http://t5.w-ga.me/FcDec13lc0hjb",
    "date": "2024-12-14"
  },
  {
    "href": "http://t5.w-ga.me/FcDec13czk8b",
    "date": "2024-12-14"
  },
  {
    "href": "http://t5.w-ga.me/FcDec13xlb99g",
    "date": "2024-12-14"
  },
  {
    "href": "http://t5.w-ga.me/FcDec13xzlb9",
    "date": "2024-12-13"
  },
  {
    "href": "http://t5.w-ga.me/FcDec12bvl0uz",
    "date": "2024-12-13"
  },
  {
    "href": "http://t5.w-ga.me/FcDec12xlc9j",
    "date": "2024-12-13"
  },
  {
    "href": "http://t5.w-ga.me/FcDec12ckx07",
    "date": "2024-12-13"
  },
  {
    "href": "http://t5.w-ga.me/LWDec12zlxc09",
    "date": "2024-12-13"
  },
  {
    "href": "http://t5.w-ga.me/FcDec12dcl08",
    "date": "2024-12-13"
  },
  {
    "href": "http://t5.w-ga.me/GeDec11xl08bv",
    "date": "2024-12-12"
  },
  {
    "href": "http://t5.w-ga.me/FcDec11clb90y",
    "date": "2024-12-12"
  },
  {
    "href": "http://t5.w-ga.me/FcDec11blk97x",
    "date": "2024-12-12"
  },
  {
    "href": "http://t5.w-ga.me/FcDec11cl907g",
    "date": "2024-12-12"
  },
  {
    "href": "http://t5.w-ga.me/GvawDec11bl0ufd",
    "date": "2024-12-12"
  },
  {
    "href": "http://t5.w-ga.me/SfDec10clbl8d",
    "date": "2024-12-11"
  },
  {
    "href": "http://t5.w-ga.me/FcDec10bkv8h",
    "date": "2024-12-11"
  },
  {
    "href": "http://t5.w-ga.me/FcDec10bl08hjc",
    "date": "2024-12-11"
  },
  {
    "href": "http://t5.w-ga.me/LWDec10l9jhg",
    "date": "2024-12-11"
  },
  {
    "href": "http://t5.w-ga.me/FtDec10blh89u",
    "date": "2024-12-11"
  },
  {
    "href": "http://t5.w-ga.me/GeDec09cl8bg",
    "date": "2024-12-10"
  },
  {
    "href": "http://t5.w-ga.me/FcDec09fck9g",
    "date": "2024-12-10"
  },
  {
    "href": "http://t5.w-ga.me/GeDec08cob8g",
    "date": "2024-12-09"
  },
  {
    "href": "http://t5.w-ga.me/FcDec08bl08g",
    "date": "2024-12-09"
  },
  {
    "href": "http://t5.w-ga.me/FcDec08nl08ya",
    "date": "2024-12-09"
  },
  {
    "href": "http://t5.w-ga.me/FcDec08cl08ga",
    "date": "2024-12-09"
  },
  {
    "href": "http://t5.w-ga.me/GvawDec08blb08gd",
    "date": "2024-12-09"
  },
  {
    "href": "http://t5.w-ga.me/SfDec07nlh8sw",
    "date": "2024-12-08"
  },
  {
    "href": "http://t5.w-ga.me/FcDec07n7ioh",
    "date": "2024-12-08"
  },
  {
    "href": "http://t5.w-ga.me/OgDec07bg7of",
    "date": "2024-12-08"
  },
  {
    "href": "http://t5.w-ga.me/ScDec07b7isa",
    "date": "2024-12-08"
  },
  {
    "href": "http://t5.w-ga.me/FtDec07bl0g89",
    "date": "2024-12-08"
  },
  {
    "href": "http://t5.w-ga.me/OgDec06bz69ih",
    "date": "2024-12-07"
  },
  {
    "href": "http://t5.w-ga.me/FcDec06vc7mv",
    "date": "2024-12-07"
  },
  {
    "href": "http://t5.w-ga.me/FcNov06cz5jg",
    "date": "2024-12-07"
  },
  {
    "href": "http://t5.w-ga.me/FcDec06hl96s",
    "date": "2024-12-06"
  },
  {
    "href": "http://t5.w-ga.me/FcDec06vb7g",
    "date": "2024-12-06"
  },
  {
    "href": "http://t5.w-ga.me/OgDec05b7bfda",
    "date": "2024-12-06"
  },
  {
    "href": "http://t5.w-ga.me/FcDec05zb7kg",
    "date": "2024-12-06"
  },
  {
    "href": "http://t5.w-ga.me/LWDec05b08gv",
    "date": "2024-12-06"
  },
  {
    "href": "http://t5.w-ga.me/FcDec05cv67k",
    "date": "2024-12-06"
  },
  {
    "href": "http://t5.w-ga.me/FcDec04xl08bg",
    "date": "2024-12-05"
  },
  {
    "href": "http://t5.w-ga.me/FcDec04cx8nb",
    "date": "2024-12-05"
  },
  {
    "href": "http://t5.w-ga.me/GvawDec04cl08b",
    "date": "2024-12-05"
  },
  {
    "href": "http://t5.w-ga.me/FcDec03xl0b8g",
    "date": "2024-12-04"
  },
  {
    "href": "http://t5.w-ga.me/LWDec03f0ukv",
    "date": "2024-12-04"
  },
  {
    "href": "http://t5.w-ga.me/FtDec03c679i",
    "date": "2024-12-04"
  },
  {
    "href": "http://t5.w-ga.me/FcDec02o08gdz",
    "date": "2024-12-03"
  },
  {
    "href": "http://t5.w-ga.me/WCBDec02czhgj",
    "date": "2024-12-03"
  },
  {
    "href": "http://t5.w-ga.me/GvawDec02glf08a",
    "date": "2024-12-03"
  },
  {
    "href": "http://t5.w-ga.me/FcDec01n79hg",
    "date": "2024-12-02"
  },
  {
    "href": "http://t5.w-ga.me/FcDec01b809g",
    "date": "2024-12-02"
  },
  {
    "href": "http://t5.w-ga.me/GvawDec01f68f",
    "date": "2024-12-02"
  },
  {
    "href": "http://t5.w-ga.me/FcNov30blg8y",
    "date": "2024-12-01"
  }
]